jaegis_mcp_server/__init__.py
jaegis_mcp_server/cli.py
jaegis_mcp_server/client.py
jaegis_mcp_server/exceptions.py
jaegis_mcp_server/server.py
jaegis_mcp_server/utils.py
manus_jaegis_mcp_server-1.0.0.data/data/share/jaegis-mcp-server/LICENSE
manus_jaegis_mcp_server-1.0.0.data/data/share/jaegis-mcp-server/README-npm.md
manus_jaegis_mcp_server-1.0.0.data/data/share/jaegis-mcp-server/package.json
manus_jaegis_mcp_server-1.0.0.dist-info/licenses/LICENSE
manus_jaegis_mcp_server-1.0.0.dist-info/METADATA
manus_jaegis_mcp_server-1.0.0.dist-info/WHEEL
manus_jaegis_mcp_server-1.0.0.dist-info/entry_points.txt
manus_jaegis_mcp_server-1.0.0.dist-info/top_level.txt
manus_jaegis_mcp_server-1.0.0.dist-info/RECORD
