Metadata-Version: 2.4
Name: manus-jaegis-mcp-server
Version: 1.0.0
Summary: JAEGIS AI Web OS MCP Server - Advanced Model Context Protocol server with filesystem, git, project management, and AI integration tools
Home-page: https://github.com/jaegis/jaegis-mcp-server
Author: JAEGIS Team
Author-email: JAEGIS Team <support@jaegis.ai>
Maintainer: JAEGIS Team
Maintainer-email: JAEGIS Team <support@jaegis.ai>
License: MIT
Project-URL: Homepage, https://github.com/jaegis/jaegis-mcp-server
Project-URL: Documentation, https://docs.jaegis.ai/mcp-server
Project-URL: Repository, https://github.com/jaegis/jaegis-mcp-server.git
Project-URL: Bug Tracker, https://github.com/jaegis/jaegis-mcp-server/issues
Project-URL: Changelog, https://github.com/jaegis/jaegis-mcp-server/blob/main/CHANGELOG.md
Project-URL: Funding, https://github.com/sponsors/jaegis
Keywords: mcp,model-context-protocol,ai,jaegis,filesystem,git,project-management,development-tools,automation,claude,anthropic,augment
Platform: any
Classifier: Development Status :: 5 - Production/Stable
Classifier: Intended Audience :: Developers
Classifier: License :: OSI Approved :: MIT License
Classifier: Operating System :: OS Independent
Classifier: Programming Language :: Python :: 3
Classifier: Programming Language :: Python :: 3.8
Classifier: Programming Language :: Python :: 3.9
Classifier: Programming Language :: Python :: 3.10
Classifier: Programming Language :: Python :: 3.11
Classifier: Programming Language :: Python :: 3.12
Classifier: Programming Language :: JavaScript
Classifier: Topic :: Software Development
Classifier: Topic :: Software Development :: Libraries :: Python Modules
Classifier: Topic :: Scientific/Engineering :: Artificial Intelligence
Classifier: Topic :: System :: Filesystems
Classifier: Topic :: Software Development :: Version Control :: Git
Classifier: Environment :: Console
Classifier: Framework :: AsyncIO
Requires-Python: >=3.8
License-File: LICENSE
Requires-Dist: click>=8.0.0
Requires-Dist: rich>=13.0.0
Requires-Dist: pyyaml>=6.0
Requires-Dist: psutil>=5.9.0
Requires-Dist: packaging>=21.0
Provides-Extra: dev
Requires-Dist: pytest>=7.0.0; extra == "dev"
Requires-Dist: pytest-asyncio>=0.21.0; extra == "dev"
Requires-Dist: pytest-cov>=4.0.0; extra == "dev"
Requires-Dist: black>=23.0.0; extra == "dev"
Requires-Dist: flake8>=6.0.0; extra == "dev"
Requires-Dist: mypy>=1.0.0; extra == "dev"
Requires-Dist: isort>=5.12.0; extra == "dev"
Requires-Dist: pre-commit>=3.0.0; extra == "dev"
Provides-Extra: docs
Requires-Dist: sphinx>=6.0.0; extra == "docs"
Requires-Dist: sphinx-rtd-theme>=1.3.0; extra == "docs"
Requires-Dist: myst-parser>=2.0.0; extra == "docs"
Provides-Extra: test
Requires-Dist: pytest>=7.0.0; extra == "test"
Requires-Dist: pytest-asyncio>=0.21.0; extra == "test"
Requires-Dist: pytest-cov>=4.0.0; extra == "test"
Requires-Dist: pytest-mock>=3.10.0; extra == "test"
Dynamic: author
Dynamic: home-page
Dynamic: license-file
Dynamic: maintainer
Dynamic: platform
Dynamic: requires-python
